README.md
setup.py
clickboxer_watertracker.egg-info/PKG-INFO
clickboxer_watertracker.egg-info/SOURCES.txt
clickboxer_watertracker.egg-info/dependency_links.txt
clickboxer_watertracker.egg-info/entry_points.txt
clickboxer_watertracker.egg-info/requires.txt
clickboxer_watertracker.egg-info/top_level.txt
wtracker/__main__.py
wtracker/app.py